CHANGELOG.txt
LICENCE.txt
MANIFEST.in
README.txt
setup.py
DigitRecognition.egg-info/SOURCES.txt
DigitRecognition.egg-info/dependency_links.txt
DigitRecognition.egg-info/requires.txt
DigitRecognition.egg-info/top_level.txt
HandWrittenDigitRecognition/__init__.py
HandWrittenDigitRecognition.egg-info/PKG-INFO
HandWrittenDigitRecognition.egg-info/SOURCES.txt
HandWrittenDigitRecognition.egg-info/dependency_links.txt
HandWrittenDigitRecognition.egg-info/requires.txt
HandWrittenDigitRecognition.egg-info/top_level.txt