Metadata-Version: 2.1
Name: HandWrittenDigitRecognition
Version: 0.0.1
Summary: A Handwritten Digit Recognition Neural Network Model: By Pranav Sai
Home-page: 
Author: Pranav Sai
Author-email: pranavs31899@gmail.com
License: MIT
Keywords: Handwritten Digit Recognition,Neural Networks
Platform: UNKNOWN
Classifier: Development Status :: 5 - Production/Stable
Classifier: Intended Audience :: Education
Classifier: Operating System :: Microsoft :: Windows :: Windows 10
Classifier: License :: OSI Approved :: MIT License
Classifier: Programming Language :: Python :: 3
License-File: LICENCE.txt
